Metadata-Version: 2.1
Name: house_price_prediction_6138
Version: 0.2
Requires-Dist: numpy
Requires-Dist: pandas
Requires-Dist: scikit-learn
Requires-Dist: scipy
